nh/__init__.py
nh-0.0.5.dist-info/licenses/LICENSE
nh-0.0.5.dist-info/METADATA
nh-0.0.5.dist-info/WHEEL
nh-0.0.5.dist-info/top_level.txt
nh-0.0.5.dist-info/RECORD
