Metadata-Version: 2.4
Name: nh
Version: 0.0.5
Summary: framework for data flow
Home-page: https://github.com/t-c-w/nh
Author: Thor Whalen
License: apache-2.0
Platform: any
License-File: LICENSE
Dynamic: license-file
